pyrefact/__init__.py
pyrefact/__main__.py
pyrefact/abstractions.py
pyrefact/constants.py
pyrefact/core.py
pyrefact/fixes.py
pyrefact/formatting.py
pyrefact/logs.py
pyrefact/main.py
pyrefact/object_oriented.py
pyrefact/parsing.py
pyrefact/pattern_matching.py
pyrefact/performance.py
pyrefact/performance_numpy.py
pyrefact/performance_pandas.py
pyrefact/processing.py
pyrefact/style.py
pyrefact/symbolic_math.py
pyrefact/tracing.py
pyrefact-100.dist-info/LICENSE
pyrefact-100.dist-info/METADATA
pyrefact-100.dist-info/WHEEL
pyrefact-100.dist-info/entry_points.txt
pyrefact-100.dist-info/top_level.txt
pyrefact-100.dist-info/RECORD
