Metadata-Version: 2.1
Name: pyrefact
Version: 100
Summary: Automated Python refactoring
Author: Olle Lindgren
Author-email: olle.ln@outlook.com
License: MIT License
Project-URL: repository, https://github.com/OlleLindgren/pyrefact
Classifier: Programming Language :: Python :: 3
Requires-Python: >=3.8
License-File: LICENSE
Requires-Dist: black>=23.1.0
Requires-Dist: compactify>=2
Requires-Dist: rmspace>=7
Requires-Dist: sympy>=1.11.0
Requires-Dist: astunparse==1.6.3; python_version < "3.9"
Provides-Extra: dev
Requires-Dist: astunparse==1.6.3; extra == "dev"
Requires-Dist: pylint==3.1.0; extra == "dev"
